gsrap/.ipynb_checkpoints/__init__-checkpoint.py
gsrap/__init__.py
gsrap/assets/.ipynb_checkpoints/PM1-checkpoint.csv
gsrap/assets/.ipynb_checkpoints/PM2A-checkpoint.csv
gsrap/assets/.ipynb_checkpoints/PM3B-checkpoint.csv
gsrap/assets/.ipynb_checkpoints/PM4A-checkpoint.csv
gsrap/assets/PM1.csv
gsrap/assets/PM2A.csv
gsrap/assets/PM3B.csv
gsrap/assets/PM4A.csv
gsrap/assets/__init__.py
gsrap/assets/kegg_compound_to_others.pickle
gsrap/assets/kegg_reaction_to_others.pickle
gsrap/commons/.ipynb_checkpoints/__init__-checkpoint.py
gsrap/commons/.ipynb_checkpoints/biomass-checkpoint.py
gsrap/commons/.ipynb_checkpoints/coeffs-checkpoint.py
gsrap/commons/.ipynb_checkpoints/downloads-checkpoint.py
gsrap/commons/.ipynb_checkpoints/escherutils-checkpoint.py
gsrap/commons/.ipynb_checkpoints/excelhub-checkpoint.py
gsrap/commons/.ipynb_checkpoints/figures-checkpoint.py
gsrap/commons/.ipynb_checkpoints/fluxbal-checkpoint.py
gsrap/commons/.ipynb_checkpoints/keggutils-checkpoint.py
gsrap/commons/.ipynb_checkpoints/logutils-checkpoint.py
gsrap/commons/.ipynb_checkpoints/medium-checkpoint.py
gsrap/commons/.ipynb_checkpoints/memoteutils-checkpoint.py
gsrap/commons/.ipynb_checkpoints/metrics-checkpoint.py
gsrap/commons/.ipynb_checkpoints/sbmlutils-checkpoint.py
gsrap/commons/__init__.py
gsrap/commons/biomass.py
gsrap/commons/coeffs.py
gsrap/commons/downloads.py
gsrap/commons/escherutils.py
gsrap/commons/excelhub.py
gsrap/commons/figures.py
gsrap/commons/fluxbal.py
gsrap/commons/keggutils.py
gsrap/commons/logutils.py
gsrap/commons/medium.py
gsrap/commons/memoteutils.py
gsrap/commons/metrics.py
gsrap/commons/sbmlutils.py
gsrap/getmaps/.ipynb_checkpoints/__init__-checkpoint.py
gsrap/getmaps/.ipynb_checkpoints/getmaps-checkpoint.py
gsrap/getmaps/.ipynb_checkpoints/kdown-checkpoint.py
gsrap/getmaps/__init__.py
gsrap/getmaps/getmaps.py
gsrap/getmaps/kdown.py
gsrap/mkmodel/.ipynb_checkpoints/__init__-checkpoint.py
gsrap/mkmodel/.ipynb_checkpoints/biologcuration-checkpoint.py
gsrap-0.10.1.dist-info/METADATA
gsrap-0.10.1.dist-info/WHEEL
gsrap-0.10.1.dist-info/entry_points.txt
gsrap-0.10.1.dist-info/licenses/LICENSE.txt
gsrap-0.10.1.dist-info/RECORD
