Metadata-Version: 2.4
Name: gsrap
Version: 0.10.1
Summary: 
License: GNU General Public License v3.0
License-File: LICENSE.txt
Author: Gioele Lazzari
Requires-Python: >=3.9
Classifier: License :: Other/Proprietary License
Classifier: Programming Language :: Python :: 3
Classifier: Programming Language :: Python :: 3.9
Classifier: Programming Language :: Python :: 3.10
Classifier: Programming Language :: Python :: 3.11
Classifier: Programming Language :: Python :: 3.12
Classifier: Programming Language :: Python :: 3.13
Classifier: Programming Language :: Python :: 3.14
Requires-Dist: biopython (>=1.80)
Requires-Dist: cobra (>=0.29)
Requires-Dist: colorlog (>=6.9.0)
Requires-Dist: escher (>=1.8.1)
Requires-Dist: gdown (>=5.2.0)
Requires-Dist: gempipe (>=1.38.1)
Requires-Dist: matplotlib (>=3.9.0)
Requires-Dist: memote (>=0.17.0)
Requires-Dist: openpyxl (>=3.1.0)
Requires-Dist: pandas (>=2.0.0)
Requires-Dist: xlsxwriter (>=3.1.0)
